{
  "matchId": "2040185",
  "homeScore": 1,
  "awayScore": 3,
  "halfTime": {
    "home": 0,
    "away": 1
  },
  "scorers": [
    {
      "team": "COL",
      "player": "穆尼奥斯",
      "minute": "38",
      "type": "goal",
      "assist": "迪亚斯"
    },
    {
      "team": "UZB",
      "player": "法伊祖拉耶夫",
      "minute": "60",
      "type": "goal"
    },
    {
      "team": "COL",
      "player": "迪亚斯",
      "minute": "65",
      "type": "goal",
      "assist": "普埃尔塔"
    },
    {
      "team": "COL",
      "player": "坎帕斯",
      "minute": "96",
      "type": "goal"
    }
  ],
  "wentToPenalties": false,
  "penaltyScore": null
}
