{
  "basic": {
    "mid": "2040301",
    "code": "周五065",
    "league": "世界杯",
    "home": "EGY",
    "away": "IRN",
    "kickoff": "2026-06-27 11:00",
    "url": "https://www.sporttery.cn/jc/zqdz/index.html?showType=2&mid=2040301",
    "scraped_at": "2026-06-26T10:51:30.771Z",
    "sale_status": "在售",
    "single_supported": {
      "HAD": false,
      "HHAD": false,
      "HAFU": true,
      "CRS": true,
      "TTG": true
    },
    "is_cancel": 0,
    "is_finished_odds": false
  },
  "odds": {
    "spf_latest": {
      "home": 2.2,
      "draw": 2.5,
      "away": 3.64
    },
    "spf_history": [],
    "handicap": -1,
    "rqspf_latest": {
      "home": 5,
      "draw": 3.7,
      "away": 1.52
    },
    "rqspf_history": [],
    "bf_latest": {
      "05:00": 300,
      "平其它": 500,
      "胜其它": 175,
      "01:00": 6.5,
      "05:02": 400,
      "05:01": 300,
      "负其它": 350,
      "02:04": 200,
      "02:05": 600,
      "02:02": 13.5,
      "02:03": 50,
      "02:00": 10,
      "02:01": 8,
      "03:03": 60,
      "03:01": 20,
      "03:02": 40,
      "03:00": 23,
      "00:01": 8,
      "00:00": 6,
      "00:03": 55,
      "00:02": 16,
      "00:05": 500,
      "00:04": 175,
      "04:02": 120,
      "04:01": 70,
      "04:00": 70,
      "01:02": 11,
      "01:01": 4.45,
      "01:04": 150,
      "01:03": 30,
      "01:05": 500
    },
    "zjq_latest": {
      "0": 6,
      "1": 3.6,
      "2": 2.8,
      "3": 4.65,
      "4": 7.5,
      "5": 18,
      "6": 34,
      "7+": 50
    },
    "bqc_latest": {
      "胜胜": 4,
      "胜平": 13.5,
      "胜负": 28,
      "平胜": 4.65,
      "平平": 3.9,
      "平负": 7,
      "负胜": 25,
      "负平": 13.5,
      "负负": 6
    }
  },
  "source": {
    "api": "getFixedBonusV1.qry",
    "fetched_at": "2026-06-26T10:51:30.771Z",
    "snapshot_time": "2026-06-26 13:28:41",
    "has_match_result": false,
    "spf_result": null,
    "half_time_result": null
  }
}