{
  "basic": {
    "mid": "2040352",
    "code": "周三080",
    "league": "世界杯",
    "home": "ENG",
    "away": "COD",
    "kickoff": "2026-07-02 00:00",
    "url": "https://www.sporttery.cn/jc/zqdz/index.html?showType=2&mid=2040352",
    "scraped_at": "2026-07-02T01:07:49.397Z",
    "sale_status": "在售",
    "single_supported": {
      "HHAD": false,
      "HAFU": true,
      "CRS": true,
      "TTG": true,
      "HAD": true
    },
    "is_cancel": 0,
    "is_finished_odds": true
  },
  "odds": {
    "spf_latest": {
      "home": 1.17,
      "draw": 5.13,
      "away": 12.5
    },
    "spf_history": [],
    "handicap": -1,
    "rqspf_latest": {
      "home": 1.64,
      "draw": 3.8,
      "away": 3.9
    },
    "rqspf_history": [],
    "bf_latest": {
      "05:00": 34,
      "平其它": 650,
      "胜其它": 32,
      "01:00": 5.8,
      "05:02": 125,
      "05:01": 50,
      "负其它": 700,
      "02:04": 700,
      "02:05": 1000,
      "02:02": 35,
      "02:03": 250,
      "02:00": 3.9,
      "02:01": 6.5,
      "03:03": 125,
      "03:01": 8.5,
      "03:02": 40,
      "03:00": 5.8,
      "00:01": 30,
      "00:00": 12.5,
      "00:03": 450,
      "00:02": 110,
      "00:05": 1000,
      "00:04": 1000,
      "04:02": 65,
      "04:01": 25,
      "04:00": 13,
      "01:02": 50,
      "01:01": 11,
      "01:04": 700,
      "01:03": 300,
      "01:05": 1000
    },
    "zjq_latest": {
      "0": 12.5,
      "1": 4.9,
      "2": 3.15,
      "3": 3.15,
      "4": 6.2,
      "5": 11.5,
      "6": 19,
      "7+": 29
    },
    "bqc_latest": {
      "胜胜": 1.57,
      "胜平": 24,
      "胜负": 90,
      "平胜": 3.65,
      "平平": 7.5,
      "平负": 27,
      "负胜": 27,
      "负平": 24,
      "负负": 24
    }
  },
  "source": {
    "api": "getFixedBonusV1.qry",
    "fetched_at": "2026-07-02T01:07:49.400Z",
    "snapshot_time": "2026-07-01 15:11:43",
    "has_match_result": true,
    "spf_result": "home",
    "half_time_result": "away"
  }
}