{
  "mid": "2040250",
  "spf_history": [
    {
      "time": "2026-06-21T11:04:17.241Z",
      "home": 6,
      "draw": 3.87,
      "away": 1.42
    }
  ],
  "rqspf_history": [
    {
      "time": "2026-06-21T11:04:17.241Z",
      "home": 2.46,
      "draw": 3.3,
      "away": 2.38
    }
  ],
  "bf_history": [
    {
      "time": "2026-06-21T11:04:17.241Z",
      "odds": {
        "05:00": 700,
        "平其它": 350,
        "胜其它": 350,
        "01:00": 14,
        "05:02": 700,
        "05:01": 500,
        "负其它": 50,
        "02:04": 60,
        "02:05": 125,
        "02:02": 17,
        "02:03": 30,
        "02:00": 35,
        "02:01": 18,
        "03:03": 60,
        "03:01": 70,
        "03:02": 70,
        "03:00": 120,
        "00:01": 5.75,
        "00:00": 10.5,
        "00:03": 10.5,
        "00:02": 5.8,
        "00:05": 60,
        "00:04": 21,
        "04:02": 250,
        "04:01": 250,
        "04:00": 400,
        "01:02": 6.5,
        "01:01": 6.8,
        "01:04": 28,
        "01:03": 11,
        "01:05": 70
      }
    }
  ],
  "zjq_history": [
    {
      "time": "2026-06-21T11:04:17.241Z",
      "odds": {
        "0": 10.5,
        "1": 4.55,
        "2": 3.1,
        "3": 3.5,
        "4": 6,
        "5": 12,
        "6": 21,
        "7+": 30
      }
    }
  ],
  "bqc_history": [
    {
      "time": "2026-06-21T11:04:17.241Z",
      "odds": {
        "胜胜": 11,
        "胜平": 18,
        "胜负": 27,
        "平胜": 12,
        "平平": 5.55,
        "平负": 4.1,
        "负胜": 50,
        "负平": 18,
        "负负": 2.05
      }
    }
  ]
}