{
  "generated_at": "2026-06-18T08:28:34.833Z",
  "note": "3 场国际赛热身，不进主建模（避免污染世界杯特征）",
  "total": 3,
  "matches": [
    {
      "mid": "2040145",
      "code": "周一201",
      "league": "国际赛",
      "home": "荷兰",
      "away": "乌兹别克",
      "home_code": "NED",
      "away_code": "UZB",
      "kickoff": "2026-06-09 02:45",
      "kickoff_iso": "2026-06-09T02:45:00+08:00",
      "handicap": -2,
      "spf": {
        "home": 1.14,
        "draw": 5.85,
        "away": 12.5
      },
      "rqspf": {
        "home": 2.65,
        "draw": 3.34,
        "away": 2.21
      },
      "scraped_at": "2026-06-17T05:49:56.298Z",
      "final_score": {
        "matchId": "2040145",
        "homeScore": 2,
        "awayScore": 1,
        "halfTime": {
          "home": 1,
          "away": 0
        },
        "scorers": [
          {
            "team": "NED",
            "player": "C. Gakpo",
            "minute": 32,
            "type": "penalty"
          },
          {
            "team": "UZB",
            "player": "I. Sergeev",
            "minute": 92,
            "type": "goal"
          },
          {
            "team": "NED",
            "player": "C. Gakpo",
            "minute": 98,
            "type": "penalty"
          }
        ],
        "wentToPenalties": false,
        "penaltyScore": null
      },
      "teams": {
        "home": {
          "code": "NED",
          "doc": {
            "name": "荷兰",
            "nameEn": "Netherlands",
            "flag": "🇳🇱"
          },
          "tier": "second",
          "stars": [
            "德容",
            "加克波"
          ],
          "has_scorer_star": true,
          "is_host": false,
          "style": "全攻全守/343",
          "confederation": "UEFA",
          "fifa_rank": null
        },
        "away": {
          "code": "UZB",
          "doc": {
            "name": "乌兹别克斯坦",
            "nameEn": "Uzbekistan",
            "flag": "🇺🇿"
          },
          "tier": "weak",
          "stars": [],
          "has_scorer_star": false,
          "is_host": false,
          "style": null,
          "confederation": "AFC",
          "fifa_rank": null
        },
        "tier_diff": 1,
        "is_derby": false,
        "has_host": false
      },
      "derived": {
        "home_goals": 2,
        "away_goals": 1,
        "total_goals": 3,
        "score_diff": 1,
        "actual_winner": "home",
        "actual_handicap_result": "home_lose",
        "spf_implied": {
          "p0_home": 0.7775615669261197,
          "p0_draw": 0.15152481817021818,
          "p0_away": 0.0709136149036621,
          "vig": 0.12813315339631148
        },
        "rqspf_implied": {
          "p0_home": 0.33416783995581495,
          "p0_draw": 0.26513316643200885,
          "p0_away": 0.40069899361217626,
          "vig": 0.1292483759536336
        },
        "spf_hit": true,
        "rqspf_hit": true,
        "movement": {
          "spf": {
            "n": 1,
            "open": {
              "home": 1.14,
              "draw": 5.85,
              "away": 12.5
            },
            "last": {
              "home": 1.14,
              "draw": 5.85,
              "away": 12.5
            },
            "delta": {
              "home": 0,
              "draw": 0,
              "away": 0
            },
            "range": {
              "home": 0,
              "draw": 0,
              "away": 0
            },
            "fav_open": "home",
            "fav_last": "home",
            "fav_drift": 0,
            "p0_open": {
              "p0_home": 0.7775615669261197,
              "p0_draw": 0.15152481817021818,
              "p0_away": 0.0709136149036621,
              "vig": 0.12813315339631148
            },
            "p0_last": {
              "p0_home": 0.7775615669261197,
              "p0_draw": 0.15152481817021818,
              "p0_away": 0.0709136149036621,
              "vig": 0.12813315339631148
            },
            "p0_delta_home": 0,
            "p0_delta_draw": 0,
            "p0_delta_away": 0
          },
          "rqspf": {
            "n": 4,
            "open": {
              "home": 2.62,
              "draw": 3.85,
              "away": 2.05
            },
            "last": {
              "home": 2.65,
              "draw": 3.34,
              "away": 2.21
            },
            "delta": {
              "home": 0.03,
              "draw": -0.51,
              "away": 0.16
            },
            "range": {
              "home": 0.16,
              "draw": 0.51,
              "away": 0.16
            },
            "fav_open": "away",
            "fav_last": "away",
            "fav_drift": 0,
            "p0_open": {
              "p0_home": 0.33800132759469814,
              "p0_draw": 0.23001648786963874,
              "p0_away": 0.43198218453566306,
              "vig": 0.12922452710201737
            },
            "p0_last": {
              "p0_home": 0.33416783995581495,
              "p0_draw": 0.26513316643200885,
              "p0_away": 0.40069899361217626,
              "vig": 0.1292483759536336
            },
            "p0_delta_home": -0.004,
            "p0_delta_draw": 0.035,
            "p0_delta_away": -0.031
          },
          "bf": {
            "n": 1,
            "open_keys": 31,
            "last_keys": 31,
            "deltas": {
              "05:00": 0,
              "平其它": 0,
              "胜其它": 0,
              "01:00": 0,
              "05:02": 0,
              "05:01": 0,
              "负其它": 0,
              "02:04": 0,
              "02:05": 0,
              "02:02": 0,
              "02:03": 0,
              "02:00": 0,
              "02:01": 0,
              "03:03": 0,
              "03:01": 0,
              "03:02": 0,
              "03:00": 0,
              "00:01": 0,
              "00:00": 0,
              "00:03": 0,
              "00:02": 0,
              "00:05": 0,
              "00:04": 0,
              "04:02": 0,
              "04:01": 0,
              "04:00": 0,
              "01:02": 0,
              "01:01": 0,
              "01:04": 0,
              "01:03": 0,
              "01:05": 0
            },
            "n_changed": 0,
            "biggest_drop": null,
            "biggest_rise": null
          },
          "zjq": {
            "n": 1,
            "open_keys": 8,
            "last_keys": 8,
            "deltas": {
              "0": 0,
              "1": 0,
              "2": 0,
              "3": 0,
              "4": 0,
              "5": 0,
              "6": 0,
              "7+": 0
            },
            "n_changed": 0,
            "biggest_drop": null,
            "biggest_rise": null
          },
          "bqc": {
            "n": 1,
            "open_keys": 9,
            "last_keys": 9,
            "deltas": {
              "胜胜": 0,
              "胜平": 0,
              "胜负": 0,
              "平胜": 0,
              "平平": 0,
              "平负": 0,
              "负胜": 0,
              "负平": 0,
              "负负": 0
            },
            "n_changed": 0,
            "biggest_drop": null,
            "biggest_rise": null
          },
          "summary": {
            "total_n": 5,
            "any_drift": 0,
            "max_abs_delta": 0.51
          }
        }
      }
    },
    {
      "mid": "2040146",
      "code": "周一202",
      "league": "国际赛",
      "home": "法国",
      "away": "北爱尔兰",
      "home_code": "FRA",
      "away_code": "NIR",
      "kickoff": "2026-06-09 03:10",
      "kickoff_iso": "2026-06-09T03:10:00+08:00",
      "handicap": -2,
      "spf": null,
      "rqspf": {
        "home": 1.82,
        "draw": 3.96,
        "away": 3.05
      },
      "scraped_at": "2026-06-17T05:49:56.430Z",
      "final_score": {
        "matchId": "2040146",
        "homeScore": 3,
        "awayScore": 1,
        "halfTime": {
          "home": 1,
          "away": 0
        },
        "scorers": [
          {
            "team": "FRA",
            "player": "M. Olise",
            "minute": 43,
            "type": "goal"
          },
          {
            "team": "FRA",
            "player": "M. Olise",
            "minute": 49,
            "type": "goal"
          },
          {
            "team": "NIR",
            "player": "P. Kelly",
            "minute": 64,
            "type": "goal"
          },
          {
            "team": "FRA",
            "player": "M. Olise",
            "minute": 75,
            "type": "goal"
          }
        ],
        "wentToPenalties": false,
        "penaltyScore": null
      },
      "teams": {
        "home": {
          "code": "FRA",
          "doc": {
            "name": "法国",
            "nameEn": "France",
            "flag": "🇫🇷"
          },
          "tier": "top",
          "stars": [
            "姆巴佩"
          ],
          "has_scorer_star": true,
          "is_host": false,
          "style": "速度+身体/姆巴佩驱动",
          "confederation": "UEFA",
          "fifa_rank": null
        },
        "away": {
          "code": "NIR",
          "doc": {
            "name": "北爱尔兰",
            "nameEn": "Northern Ireland",
            "flag": "🇬🇧"
          },
          "tier": "weak",
          "stars": [],
          "has_scorer_star": false,
          "is_host": false,
          "style": "英式/防守",
          "confederation": "UEFA",
          "fifa_rank": null
        },
        "tier_diff": 2,
        "is_derby": true,
        "has_host": false
      },
      "derived": {
        "home_goals": 3,
        "away_goals": 1,
        "total_goals": 4,
        "score_diff": 2,
        "actual_winner": "home",
        "actual_handicap_result": "draw",
        "spf_implied": null,
        "rqspf_implied": {
          "p0_home": 0.4863062787382933,
          "p0_draw": 0.22350440083426618,
          "p0_away": 0.29018932042744067,
          "vig": 0.12984465443481819
        },
        "spf_hit": null,
        "rqspf_hit": false,
        "movement": {
          "spf": {
            "n": 0,
            "open": null,
            "last": null,
            "delta": null,
            "range": null,
            "fav_open": null,
            "fav_last": null,
            "fav_drift": null,
            "p0_open": null,
            "p0_last": null,
            "p0_delta_home": null,
            "p0_delta_draw": null,
            "p0_delta_away": null
          },
          "rqspf": {
            "n": 4,
            "open": {
              "home": 1.92,
              "draw": 3.9,
              "away": 2.85
            },
            "last": {
              "home": 1.82,
              "draw": 3.96,
              "away": 3.05
            },
            "delta": {
              "home": -0.1,
              "draw": 0.06,
              "away": 0.2
            },
            "range": {
              "home": 0.13,
              "draw": 0.36,
              "away": 0.2
            },
            "fav_open": "home",
            "fav_last": "home",
            "fav_drift": 0,
            "p0_open": {
              "p0_home": 0.4616822429906542,
              "p0_draw": 0.22728971962616823,
              "p0_away": 0.3110280373831775,
              "vig": 0.128120782726046
            },
            "p0_last": {
              "p0_home": 0.4863062787382933,
              "p0_draw": 0.22350440083426618,
              "p0_away": 0.29018932042744067,
              "vig": 0.12984465443481819
            },
            "p0_delta_home": 0.025,
            "p0_delta_draw": -0.004,
            "p0_delta_away": -0.021
          },
          "bf": {
            "n": 1,
            "open_keys": 31,
            "last_keys": 31,
            "deltas": {
              "05:00": 0,
              "平其它": 0,
              "胜其它": 0,
              "01:00": 0,
              "05:02": 0,
              "05:01": 0,
              "负其它": 0,
              "02:04": 0,
              "02:05": 0,
              "02:02": 0,
              "02:03": 0,
              "02:00": 0,
              "02:01": 0,
              "03:03": 0,
              "03:01": 0,
              "03:02": 0,
              "03:00": 0,
              "00:01": 0,
              "00:00": 0,
              "00:03": 0,
              "00:02": 0,
              "00:05": 0,
              "00:04": 0,
              "04:02": 0,
              "04:01": 0,
              "04:00": 0,
              "01:02": 0,
              "01:01": 0,
              "01:04": 0,
              "01:03": 0,
              "01:05": 0
            },
            "n_changed": 0,
            "biggest_drop": null,
            "biggest_rise": null
          },
          "zjq": {
            "n": 1,
            "open_keys": 8,
            "last_keys": 8,
            "deltas": {
              "0": 0,
              "1": 0,
              "2": 0,
              "3": 0,
              "4": 0,
              "5": 0,
              "6": 0,
              "7+": 0
            },
            "n_changed": 0,
            "biggest_drop": null,
            "biggest_rise": null
          },
          "bqc": {
            "n": 1,
            "open_keys": 9,
            "last_keys": 9,
            "deltas": {
              "胜胜": 0,
              "胜平": 0,
              "胜负": 0,
              "平胜": 0,
              "平平": 0,
              "平负": 0,
              "负胜": 0,
              "负平": 0,
              "负负": 0
            },
            "n_changed": 0,
            "biggest_drop": null,
            "biggest_rise": null
          },
          "summary": {
            "total_n": 4,
            "any_drift": 0,
            "max_abs_delta": 0.2
          }
        }
      }
    },
    {
      "mid": "2040147",
      "code": "周一203",
      "league": "国际赛",
      "home": "秘鲁",
      "away": "西班牙",
      "home_code": "PER",
      "away_code": "ESP",
      "kickoff": "2026-06-09 10:00",
      "kickoff_iso": "2026-06-09T10:00:00+08:00",
      "handicap": 2,
      "spf": null,
      "rqspf": {
        "home": 2.38,
        "draw": 3.4,
        "away": 2.41
      },
      "scraped_at": "2026-06-17T05:49:56.641Z",
      "final_score": {
        "matchId": "2040147",
        "homeScore": 1,
        "awayScore": 3,
        "halfTime": {
          "home": 0,
          "away": 2
        },
        "scorers": [
          {
            "team": "ESP",
            "player": "M. Oyarzabal",
            "minute": 2,
            "type": "goal"
          },
          {
            "team": "ESP",
            "player": "Pedri",
            "minute": 32,
            "type": "goal"
          },
          {
            "team": "ESP",
            "player": "P. Gallese",
            "minute": 53,
            "type": "og"
          },
          {
            "team": "PER",
            "player": "J. Vélez",
            "minute": 66,
            "type": "goal"
          }
        ],
        "wentToPenalties": false,
        "penaltyScore": null
      },
      "teams": {
        "home": {
          "code": "PER",
          "doc": {
            "name": "秘鲁",
            "nameEn": "Peru",
            "flag": "🇵🇪"
          },
          "tier": "weak",
          "stars": [],
          "has_scorer_star": false,
          "is_host": false,
          "style": "南美/技术",
          "confederation": "CONMEBOL",
          "fifa_rank": null
        },
        "away": {
          "code": "ESP",
          "doc": {
            "name": "西班牙",
            "nameEn": "Spain",
            "flag": "🇪🇸"
          },
          "tier": "second",
          "stars": [
            "亚马尔",
            "罗德里"
          ],
          "has_scorer_star": true,
          "is_host": false,
          "style": "传控/年轻阵容",
          "confederation": "UEFA",
          "fifa_rank": null
        },
        "tier_diff": -1,
        "is_derby": false,
        "has_host": false
      },
      "derived": {
        "home_goals": 1,
        "away_goals": 3,
        "total_goals": 4,
        "score_diff": -2,
        "actual_winner": "away",
        "actual_handicap_result": "draw",
        "spf_implied": null,
        "rqspf_implied": {
          "p0_home": 0.37208584221090013,
          "p0_draw": 0.2604600895476301,
          "p0_away": 0.3674540682414698,
          "vig": 0.12922347362181386
        },
        "spf_hit": null,
        "rqspf_hit": false,
        "movement": {
          "spf": {
            "n": 0,
            "open": null,
            "last": null,
            "delta": null,
            "range": null,
            "fav_open": null,
            "fav_last": null,
            "fav_drift": null,
            "p0_open": null,
            "p0_last": null,
            "p0_delta_home": null,
            "p0_delta_draw": null,
            "p0_delta_away": null
          },
          "rqspf": {
            "n": 4,
            "open": {
              "home": 2.68,
              "draw": 3.85,
              "away": 2.02
            },
            "last": {
              "home": 2.38,
              "draw": 3.4,
              "away": 2.41
            },
            "delta": {
              "home": -0.3,
              "draw": -0.45,
              "away": 0.39
            },
            "range": {
              "home": 0.3,
              "draw": 0.45,
              "away": 0.39
            },
            "fav_open": "away",
            "fav_last": "home",
            "fav_drift": 1,
            "p0_open": {
              "p0_home": 0.33081510596122266,
              "p0_draw": 0.23028168414963032,
              "p0_away": 0.43890320988914694,
              "vig": 0.1279240930489638
            },
            "p0_last": {
              "p0_home": 0.37208584221090013,
              "p0_draw": 0.2604600895476301,
              "p0_away": 0.3674540682414698,
              "vig": 0.12922347362181386
            },
            "p0_delta_home": 0.041,
            "p0_delta_draw": 0.03,
            "p0_delta_away": -0.071
          },
          "bf": {
            "n": 1,
            "open_keys": 31,
            "last_keys": 31,
            "deltas": {
              "05:00": 0,
              "平其它": 0,
              "胜其它": 0,
              "01:00": 0,
              "05:02": 0,
              "05:01": 0,
              "负其它": 0,
              "02:04": 0,
              "02:05": 0,
              "02:02": 0,
              "02:03": 0,
              "02:00": 0,
              "02:01": 0,
              "03:03": 0,
              "03:01": 0,
              "03:02": 0,
              "03:00": 0,
              "00:01": 0,
              "00:00": 0,
              "00:03": 0,
              "00:02": 0,
              "00:05": 0,
              "00:04": 0,
              "04:02": 0,
              "04:01": 0,
              "04:00": 0,
              "01:02": 0,
              "01:01": 0,
              "01:04": 0,
              "01:03": 0,
              "01:05": 0
            },
            "n_changed": 0,
            "biggest_drop": null,
            "biggest_rise": null
          },
          "zjq": {
            "n": 1,
            "open_keys": 8,
            "last_keys": 8,
            "deltas": {
              "0": 0,
              "1": 0,
              "2": 0,
              "3": 0,
              "4": 0,
              "5": 0,
              "6": 0,
              "7+": 0
            },
            "n_changed": 0,
            "biggest_drop": null,
            "biggest_rise": null
          },
          "bqc": {
            "n": 1,
            "open_keys": 9,
            "last_keys": 9,
            "deltas": {
              "胜胜": 0,
              "胜平": 0,
              "胜负": 0,
              "平胜": 0,
              "平平": 0,
              "平负": 0,
              "负胜": 0,
              "负平": 0,
              "负负": 0
            },
            "n_changed": 0,
            "biggest_drop": null,
            "biggest_rise": null
          },
          "summary": {
            "total_n": 4,
            "any_drift": 1,
            "max_abs_delta": 0.45
          }
        }
      }
    }
  ]
}
