{
  "basic": {
    "mid": "1016205",
    "code": "2022-C3",
    "league": "世界杯",
    "home": "波兰",
    "away": "沙特阿拉伯",
    "kickoff": "2022-11-26 20:00",
    "url": "https://www.sporttery.cn/jc/zqdz/index.html?showType=2&mid=1016205",
    "scraped_at": "2026-06-19T06:51:39.633Z",
    "sale_status": "已完赛",
    "single_supported": {
      "HHAD": false,
      "HAFU": true,
      "CRS": true,
      "TTG": true,
      "HAD": false
    },
    "is_cancel": 0,
    "is_finished_odds": true
  },
  "odds": {
    "spf_latest": {
      "home": 1.53,
      "draw": 3.35,
      "away": 5.35
    },
    "spf_history": [
      {
        "a": "4.95",
        "updateDate": "2022-11-24",
        "df": "0",
        "d": "3.25",
        "af": "0",
        "h": "1.59",
        "updateTime": "09:28:20",
        "hf": "0",
        "goalLine": ""
      },
      {
        "a": "4.68",
        "updateDate": "2022-11-26",
        "df": "0",
        "d": "3.25",
        "af": "-1",
        "h": "1.62",
        "updateTime": "14:40:44",
        "hf": "1",
        "goalLine": ""
      },
      {
        "a": "4.60",
        "updateDate": "2022-11-26",
        "df": "-1",
        "d": "3.20",
        "af": "-1",
        "h": "1.64",
        "updateTime": "15:20:00",
        "hf": "1",
        "goalLine": ""
      },
      {
        "a": "4.95",
        "updateDate": "2022-11-26",
        "df": "1",
        "d": "3.25",
        "af": "1",
        "h": "1.59",
        "updateTime": "20:19:36",
        "hf": "-1",
        "goalLine": ""
      },
      {
        "a": "5.15",
        "updateDate": "2022-11-26",
        "df": "1",
        "d": "3.30",
        "af": "1",
        "h": "1.56",
        "updateTime": "20:40:24",
        "hf": "-1",
        "goalLine": ""
      },
      {
        "a": "5.35",
        "updateDate": "2022-11-26",
        "df": "1",
        "d": "3.35",
        "af": "1",
        "h": "1.53",
        "updateTime": "20:51:12",
        "hf": "-1",
        "goalLine": ""
      }
    ],
    "handicap": -1,
    "rqspf_latest": {
      "home": 2.95,
      "draw": 3.1,
      "away": 2.1
    },
    "rqspf_history": [
      {
        "a": "2.00",
        "updateDate": "2022-11-24",
        "df": "0",
        "d": "3.11",
        "af": "0",
        "h": "3.15",
        "updateTime": "09:28:20",
        "hf": "0",
        "goalLine": "-1"
      },
      {
        "a": "1.97",
        "updateDate": "2022-11-26",
        "df": "0",
        "d": "3.11",
        "af": "-1",
        "h": "3.22",
        "updateTime": "14:40:56",
        "hf": "1",
        "goalLine": "-1"
      },
      {
        "a": "1.94",
        "updateDate": "2022-11-26",
        "df": "1",
        "d": "3.15",
        "af": "-1",
        "h": "3.26",
        "updateTime": "15:19:53",
        "hf": "1",
        "goalLine": "-1"
      },
      {
        "a": "2.00",
        "updateDate": "2022-11-26",
        "df": "-1",
        "d": "3.11",
        "af": "1",
        "h": "3.15",
        "updateTime": "20:19:42",
        "hf": "-1",
        "goalLine": "-1"
      },
      {
        "a": "2.05",
        "updateDate": "2022-11-26",
        "df": "-1",
        "d": "3.10",
        "af": "1",
        "h": "3.05",
        "updateTime": "20:40:31",
        "hf": "-1",
        "goalLine": "-1"
      },
      {
        "a": "2.10",
        "updateDate": "2022-11-26",
        "df": "0",
        "d": "3.10",
        "af": "1",
        "h": "2.95",
        "updateTime": "20:51:21",
        "hf": "-1",
        "goalLine": "-1"
      }
    ],
    "bf_latest": {
      "05:00": 70,
      "平其它": 300,
      "胜其它": 60,
      "01:00": 5.5,
      "05:02": 150,
      "05:01": 80,
      "负其它": 200,
      "02:04": 150,
      "02:05": 400,
      "02:02": 18,
      "02:03": 50,
      "02:00": 7,
      "02:01": 7,
      "03:03": 75,
      "03:01": 16,
      "03:02": 32,
      "03:00": 15,
      "00:01": 10,
      "00:00": 7.5,
      "00:03": 60,
      "00:02": 20,
      "00:05": 500,
      "00:04": 200,
      "04:02": 75,
      "04:01": 35,
      "04:00": 33,
      "01:02": 11,
      "01:01": 5.95,
      "01:04": 150,
      "01:03": 37,
      "01:05": 400
    },
    "bf_history": [
      {
        "s05s00": "60.00",
        "s-1sd": "500.0",
        "s02s00f": "0",
        "s-1sh": "60.00",
        "s01s00": "5.60",
        "s05s02": "150.0",
        "s05s01": "70.00",
        "s-1sa": "250.0",
        "s00s03f": "0",
        "s02s04f": "0",
        "s04s01f": "0",
        "s03s00f": "0",
        "s01s03f": "0",
        "s02s04": "250.0",
        "s02s05": "700.0",
        "s02s02": "16.00",
        "s02s03": "50.00",
        "s05s01f": "0",
        "s02s00": "6.50",
        "s02s01": "7.00",
        "s02s05f": "0",
        "s00s02f": "0",
        "s02s01f": "0",
        "s04s00f": "0",
        "goalLine": "",
        "s03s01f": "0",
        "s-1sdf": "0",
        "s-1shf": "0",
        "s01s02f": "0",
        "s03s03": "80.00",
        "s05s00f": "0",
        "updateDate": "2022-11-24",
        "s03s01": "13.00",
        "s03s02": "28.00",
        "s03s00": "11.00",
        "s00s01f": "0",
        "s02s02f": "0",
        "s00s05f": "0",
        "s00s01": "10.50",
        "s00s00": "9.00",
        "s00s03": "70.00",
        "s01s01f": "0",
        "s00s02": "25.00",
        "s00s05": "800.0",
        "s00s04": "250.0",
        "s01s05f": "0",
        "s03s02f": "0",
        "s04s02": "60.00",
        "s04s01": "30.00",
        "s04s00": "25.00",
        "s00s00f": "0",
        "updateTime": "09:28:20",
        "s00s04f": "0",
        "s-1saf": "0",
        "s02s03f": "0",
        "s04s02f": "0",
        "s01s02": "14.00",
        "s01s01": "6.10",
        "s01s04": "200.0",
        "s01s00f": "0",
        "s01s03": "50.00",
        "s05s02f": "0",
        "s01s05": "600.0",
        "s03s03f": "0",
        "s01s04f": "0"
      },
      {
        "s05s00": "60.00",
        "s-1sd": "300.0",
        "s02s00f": "0",
        "s-1sh": "55.00",
        "s01s00": "5.60",
        "s05s02": "125.0",
        "s05s01": "70.00",
        "s-1sa": "200.0",
        "s00s03f": "0",
        "s02s04f": "-1",
        "s04s01f": "0",
        "s03s00f": "0",
        "s01s03f": "0",
        "s02s04": "200.0",
        "s02s05": "500.0",
        "s02s02": "17.00",
        "s02s03": "50.00",
        "s05s01f": "0",
        "s02s00": "6.50",
        "s02s01": "7.00",
        "s02s05f": "-1",
        "s00s02f": "0",
        "s02s01f": "0",
        "s04s00f": "0",
        "goalLine": "",
        "s03s01f": "1",
        "s-1sdf": "-1",
        "s-1shf": "-1",
        "s01s02f": "-1",
        "s03s03": "75.00",
        "s05s00f": "0",
        "updateDate": "2022-11-26",
        "s03s01": "13.50",
        "s03s02": "30.00",
        "s03s00": "11.00",
        "s00s01f": "1",
        "s02s02f": "1",
        "s00s05f": "-1",
        "s00s01": "10.75",
        "s00s00": "9.00",
        "s00s03": "70.00",
        "s01s01f": "0",
        "s00s02": "25.00",
        "s00s05": "600.0",
        "s00s04": "200.0",
        "s01s05f": "-1",
        "s03s02f": "1",
        "s04s02": "65.00",
        "s04s01": "30.00",
        "s04s00": "25.00",
        "s00s00f": "0",
        "updateTime": "09:00:17",
        "s00s04f": "-1",
        "s-1saf": "-1",
        "s02s03f": "0",
        "s04s02f": "1",
        "s01s02": "13.50",
        "s01s01": "6.10",
        "s01s04": "150.0",
        "s01s00f": "0",
        "s01s03": "50.00",
        "s05s02f": "-1",
        "s01s05": "400.0",
        "s03s03f": "-1",
        "s01s04f": "-1"
      },
      {
        "s05s00": "70.00",
        "s-1sd": "300.0",
        "s02s00f": "0",
        "s-1sh": "55.00",
        "s01s00": "5.50",
        "s05s02": "125.0",
        "s05s01": "80.00",
        "s-1sa": "200.0",
        "s00s03f": "0",
        "s02s04f": "0",
        "s04s01f": "0",
        "s03s00f": "0",
        "s01s03f": "0",
        "s02s04": "200.0",
        "s02s05": "500.0",
        "s02s02": "18.00",
        "s02s03": "50.00",
        "s05s01f": "1",
        "s02s00": "6.50",
        "s02s01": "7.00",
        "s02s05f": "0",
        "s00s02f": "-1",
        "s02s01f": "0",
        "s04s00f": "1",
        "goalLine": "",
        "s03s01f": "0",
        "s-1sdf": "0",
        "s-1shf": "0",
        "s01s02f": "0",
        "s03s03": "75.00",
        "s05s00f": "1",
        "updateDate": "2022-11-26",
        "s03s01": "13.50",
        "s03s02": "32.00",
        "s03s00": "11.00",
        "s00s01f": "0",
        "s02s02f": "1",
        "s00s05f": "0",
        "s00s01": "10.75",
        "s00s00": "8.50",
        "s00s03": "70.00",
        "s01s01f": "-1",
        "s00s02": "24.00",
        "s00s05": "600.0",
        "s00s04": "200.0",
        "s01s05f": "0",
        "s03s02f": "1",
        "s04s02": "75.00",
        "s04s01": "30.00",
        "s04s00": "28.00",
        "s00s00f": "-1",
        "updateTime": "14:03:56",
        "s00s04f": "0",
        "s-1saf": "0",
        "s02s03f": "0",
        "s04s02f": "1",
        "s01s02": "13.50",
        "s01s01": "5.95",
        "s01s04": "150.0",
        "s01s00f": "-1",
        "s01s03": "50.00",
        "s05s02f": "0",
        "s01s05": "400.0",
        "s03s03f": "0",
        "s01s04f": "0"
      },
      {
        "s05s00": "70.00",
        "s-1sd": "300.0",
        "s02s00f": "0",
        "s-1sh": "60.00",
        "s01s00": "5.50",
        "s05s02": "150.0",
        "s05s01": "80.00",
        "s-1sa": "200.0",
        "s00s03f": "0",
        "s02s04f": "0",
        "s04s01f": "1",
        "s03s00f": "1",
        "s01s03f": "0",
        "s02s04": "200.0",
        "s02s05": "500.0",
        "s02s02": "18.00",
        "s02s03": "50.00",
        "s05s01f": "0",
        "s02s00": "6.50",
        "s02s01": "7.00",
        "s02s05f": "0",
        "s00s02f": "0",
        "s02s01f": "0",
        "s04s00f": "1",
        "goalLine": "",
        "s03s01f": "1",
        "s-1sdf": "0",
        "s-1shf": "1",
        "s01s02f": "0",
        "s03s03": "75.00",
        "s05s00f": "0",
        "updateDate": "2022-11-26",
        "s03s01": "14.00",
        "s03s02": "32.00",
        "s03s00": "13.00",
        "s00s01f": "-1",
        "s02s02f": "0",
        "s00s05f": "0",
        "s00s01": "10.00",
        "s00s00": "7.50",
        "s00s03": "70.00",
        "s01s01f": "0",
        "s00s02": "24.00",
        "s00s05": "600.0",
        "s00s04": "200.0",
        "s01s05f": "0",
        "s03s02f": "0",
        "s04s02": "75.00",
        "s04s01": "32.00",
        "s04s00": "30.00",
        "s00s00f": "-1",
        "updateTime": "16:53:44",
        "s00s04f": "0",
        "s-1saf": "0",
        "s02s03f": "0",
        "s04s02f": "0",
        "s01s02": "13.50",
        "s01s01": "5.95",
        "s01s04": "150.0",
        "s01s00f": "0",
        "s01s03": "50.00",
        "s05s02f": "1",
        "s01s05": "400.0",
        "s03s03f": "0",
        "s01s04f": "0"
      },
      {
        "s05s00": "70.00",
        "s-1sd": "300.0",
        "s02s00f": "1",
        "s-1sh": "60.00",
        "s01s00": "5.50",
        "s05s02": "150.0",
        "s05s01": "80.00",
        "s-1sa": "200.0",
        "s00s03f": "-1",
        "s02s04f": "-1",
        "s04s01f": "1",
        "s03s00f": "1",
        "s01s03f": "-1",
        "s02s04": "150.0",
        "s02s05": "400.0",
        "s02s02": "18.00",
        "s02s03": "50.00",
        "s05s01f": "0",
        "s02s00": "6.75",
        "s02s01": "7.00",
        "s02s05f": "-1",
        "s00s02f": "-1",
        "s02s01f": "0",
        "s04s00f": "0",
        "goalLine": "",
        "s03s01f": "1",
        "s-1sdf": "0",
        "s-1shf": "0",
        "s01s02f": "-1",
        "s03s03": "75.00",
        "s05s00f": "0",
        "updateDate": "2022-11-26",
        "s03s01": "15.00",
        "s03s02": "32.00",
        "s03s00": "14.00",
        "s00s01f": "0",
        "s02s02f": "0",
        "s00s05f": "-1",
        "s00s01": "10.00",
        "s00s00": "7.50",
        "s00s03": "60.00",
        "s01s01f": "0",
        "s00s02": "22.00",
        "s00s05": "500.0",
        "s00s04": "200.0",
        "s01s05f": "0",
        "s03s02f": "0",
        "s04s02": "75.00",
        "s04s01": "35.00",
        "s04s00": "30.00",
        "s00s00f": "0",
        "updateTime": "17:25:32",
        "s00s04f": "0",
        "s-1saf": "0",
        "s02s03f": "0",
        "s04s02f": "0",
        "s01s02": "12.50",
        "s01s01": "5.95",
        "s01s04": "150.0",
        "s01s00f": "0",
        "s01s03": "40.00",
        "s05s02f": "0",
        "s01s05": "400.0",
        "s03s03f": "0",
        "s01s04f": "0"
      },
      {
        "s05s00": "70.00",
        "s-1sd": "300.0",
        "s02s00f": "1",
        "s-1sh": "60.00",
        "s01s00": "5.50",
        "s05s02": "150.0",
        "s05s01": "80.00",
        "s-1sa": "200.0",
        "s00s03f": "0",
        "s02s04f": "0",
        "s04s01f": "0",
        "s03s00f": "1",
        "s01s03f": "-1",
        "s02s04": "150.0",
        "s02s05": "400.0",
        "s02s02": "18.00",
        "s02s03": "50.00",
        "s05s01f": "0",
        "s02s00": "7.00",
        "s02s01": "7.00",
        "s02s05f": "0",
        "s00s02f": "-1",
        "s02s01f": "0",
        "s04s00f": "1",
        "goalLine": "",
        "s03s01f": "1",
        "s-1sdf": "0",
        "s-1shf": "0",
        "s01s02f": "-1",
        "s03s03": "75.00",
        "s05s00f": "0",
        "updateDate": "2022-11-26",
        "s03s01": "16.00",
        "s03s02": "32.00",
        "s03s00": "15.00",
        "s00s01f": "0",
        "s02s02f": "0",
        "s00s05f": "0",
        "s00s01": "10.00",
        "s00s00": "7.50",
        "s00s03": "60.00",
        "s01s01f": "0",
        "s00s02": "20.00",
        "s00s05": "500.0",
        "s00s04": "200.0",
        "s01s05f": "0",
        "s03s02f": "0",
        "s04s02": "75.00",
        "s04s01": "35.00",
        "s04s00": "33.00",
        "s00s00f": "0",
        "updateTime": "19:52:56",
        "s00s04f": "0",
        "s-1saf": "0",
        "s02s03f": "0",
        "s04s02f": "0",
        "s01s02": "11.00",
        "s01s01": "5.95",
        "s01s04": "150.0",
        "s01s00f": "0",
        "s01s03": "37.00",
        "s05s02f": "0",
        "s01s05": "400.0",
        "s03s03f": "0",
        "s01s04f": "0"
      }
    ],
    "zjq_latest": {
      "0": 7.5,
      "1": 4,
      "2": 3.2,
      "3": 3.95,
      "4": 7,
      "5": 12,
      "6": 23,
      "7+": 30
    },
    "zjq_history": [
      {
        "s3": "3.75",
        "s4": "6.20",
        "updateDate": "2022-11-24",
        "s5": "11.00",
        "s6f": "0",
        "s6": "22.00",
        "s7f": "0",
        "s4f": "0",
        "s7": "30.00",
        "s5f": "0",
        "s2f": "0",
        "s3f": "0",
        "s0f": "0",
        "s1f": "0",
        "updateTime": "09:28:20",
        "goalLine": "",
        "s0": "9.00",
        "s1": "4.50",
        "s2": "3.10"
      },
      {
        "s3": "3.75",
        "s4": "6.50",
        "updateDate": "2022-11-26",
        "s5": "12.00",
        "s6f": "1",
        "s6": "23.00",
        "s7f": "0",
        "s4f": "1",
        "s7": "30.00",
        "s5f": "1",
        "s2f": "0",
        "s3f": "0",
        "s0f": "-1",
        "s1f": "-1",
        "updateTime": "14:03:39",
        "goalLine": "",
        "s0": "8.50",
        "s1": "4.30",
        "s2": "3.10"
      },
      {
        "s3": "3.95",
        "s4": "7.00",
        "updateDate": "2022-11-26",
        "s5": "12.00",
        "s6f": "0",
        "s6": "23.00",
        "s7f": "0",
        "s4f": "1",
        "s7": "30.00",
        "s5f": "0",
        "s2f": "1",
        "s3f": "1",
        "s0f": "-1",
        "s1f": "-1",
        "updateTime": "16:53:32",
        "goalLine": "",
        "s0": "7.50",
        "s1": "4.00",
        "s2": "3.20"
      }
    ],
    "bqc_latest": {
      "胜胜": 2.45,
      "胜平": 17,
      "胜负": 28,
      "平胜": 4.1,
      "平平": 5,
      "平负": 10.5,
      "负胜": 24,
      "负平": 17,
      "负负": 9
    },
    "bqc_history": [
      {
        "aa": "8.00",
        "dd": "4.90",
        "hh": "2.40",
        "updateDate": "2022-11-24",
        "adf": "0",
        "ad": "18.00",
        "dhf": "0",
        "dh": "4.15",
        "aaf": "0",
        "ah": "27.00",
        "ddf": "0",
        "hhf": "0",
        "daf": "0",
        "updateTime": "09:28:20",
        "hdf": "0",
        "haf": "0",
        "goalLine": "",
        "ha": "50.00",
        "hd": "18.00",
        "da": "10.00",
        "ahf": "0"
      },
      {
        "aa": "8.00",
        "dd": "4.90",
        "hh": "2.45",
        "updateDate": "2022-11-25",
        "adf": "0",
        "ad": "18.00",
        "dhf": "0",
        "dh": "4.15",
        "aaf": "0",
        "ah": "27.00",
        "ddf": "0",
        "hhf": "1",
        "daf": "0",
        "updateTime": "17:54:45",
        "hdf": "0",
        "haf": "-1",
        "goalLine": "",
        "ha": "35.00",
        "hd": "18.00",
        "da": "10.00",
        "ahf": "0"
      },
      {
        "aa": "8.25",
        "dd": "5.00",
        "hh": "2.45",
        "updateDate": "2022-11-26",
        "adf": "-1",
        "ad": "17.00",
        "dhf": "1",
        "dh": "4.25",
        "aaf": "1",
        "ah": "24.00",
        "ddf": "1",
        "hhf": "0",
        "daf": "1",
        "updateTime": "10:16:02",
        "hdf": "-1",
        "haf": "-1",
        "goalLine": "",
        "ha": "28.00",
        "hd": "17.00",
        "da": "10.50",
        "ahf": "-1"
      },
      {
        "aa": "9.00",
        "dd": "5.00",
        "hh": "2.45",
        "updateDate": "2022-11-26",
        "adf": "0",
        "ad": "17.00",
        "dhf": "-1",
        "dh": "4.10",
        "aaf": "1",
        "ah": "24.00",
        "ddf": "0",
        "hhf": "0",
        "daf": "0",
        "updateTime": "20:51:46",
        "hdf": "0",
        "haf": "0",
        "goalLine": "",
        "ha": "28.00",
        "hd": "17.00",
        "da": "10.50",
        "ahf": "0"
      }
    ]
  },
  "lottery": {
    "HHAD": {
      "combination": "H",
      "combinationDesc": "(-1)胜",
      "odds": 2.95
    },
    "HAFU": {
      "combination": "H:H",
      "combinationDesc": "胜胜",
      "odds": 2.45
    },
    "CRS": {
      "combination": "2:0",
      "combinationDesc": "2:0",
      "odds": 7
    },
    "TTG": {
      "combination": "2",
      "combinationDesc": "2",
      "odds": 3.2
    },
    "HAD": {
      "combination": "H",
      "combinationDesc": "胜",
      "odds": 1.53
    }
  },
  "source": {
    "api": "getFixedBonusV1.qry",
    "fetched_at": "2026-06-19T06:51:39.633Z",
    "snapshot_time": "2022-11-26 20:51:12",
    "full_time_score": "2:0"
  }
}
